komparse_gen/__init__.py
komparse_gen/generator.py
komparse_gen/grammar.py
komparse_gen/output.py
komparse_generator-1.0.1.dist-info/LICENSE-2.0.txt
komparse_generator-1.0.1.dist-info/METADATA
komparse_generator-1.0.1.dist-info/WHEEL
komparse_generator-1.0.1.dist-info/entry_points.txt
komparse_generator-1.0.1.dist-info/top_level.txt
komparse_generator-1.0.1.dist-info/RECORD
